torchmesh/__init__.py
torchmesh/boundaries/__init__.py
torchmesh/boundaries/_boundary_extraction.py
torchmesh/boundaries/_cleaning.py
torchmesh/boundaries/_detection.py
torchmesh/boundaries/_facet_extraction.py
torchmesh/boundaries/_topology.py
torchmesh/calculus/README.md
torchmesh/calculus/__init__.py
torchmesh/calculus/_circumcentric_dual.py
torchmesh/calculus/_exterior_derivative.py
torchmesh/calculus/_hodge_star.py
torchmesh/calculus/_lsq_intrinsic.py
torchmesh/calculus/_lsq_reconstruction.py
torchmesh/calculus/_pca_tangent.py
torchmesh/calculus/_sharp_flat.py
torchmesh/calculus/curl.py
torchmesh/calculus/derivatives.py
torchmesh/calculus/divergence.py
torchmesh/calculus/gradient.py
torchmesh/calculus/laplacian.py
torchmesh/curvature/__init__.py
torchmesh/curvature/_angles.py
torchmesh/curvature/_laplacian.py
torchmesh/curvature/_utils.py
torchmesh/curvature/gaussian.py
torchmesh/curvature/mean.py
torchmesh/examples/README.md
torchmesh/examples/__init__.py
torchmesh/examples/basic/__init__.py
torchmesh/examples/basic/single_edge_2d.py
torchmesh/examples/basic/single_edge_3d.py
torchmesh/examples/basic/single_point_2d.py
torchmesh/examples/basic/single_point_3d.py
torchmesh/examples/basic/single_tetrahedron.py
torchmesh/examples/basic/single_triangle_2d.py
torchmesh/examples/basic/single_triangle_3d.py
torchmesh/examples/basic/three_edges_2d.py
torchmesh/examples/basic/three_edges_3d.py
torchmesh/examples/basic/three_points_2d.py
torchmesh/examples/basic/three_points_3d.py
torchmesh/examples/basic/two_tetrahedra.py
torchmesh/examples/basic/two_triangles_2d.py
torchmesh/examples/basic/two_triangles_3d.py
torchmesh/examples/curves/__init__.py
torchmesh/examples/curves/circle_2d.py
torchmesh/examples/curves/circle_3d.py
torchmesh/examples/curves/circular_arc_2d.py
torchmesh/examples/curves/ellipse_2d.py
torchmesh/examples/curves/helix_3d.py
torchmesh/examples/curves/line_segment_1d.py
torchmesh/examples/curves/line_segments_1d.py
torchmesh-0.1.0.dist-info/WHEEL
torchmesh-0.1.0.dist-info/METADATA
torchmesh-0.1.0.dist-info/RECORD
