Metadata-Version: 2.3
Name: torchmesh
Version: 0.1.0
Summary: GPU-Accelerated Mesh Processing for Physical Simulation and Scientific Visualization in Any Dimension
Keywords: mesh,pytorch,gpu,cfd,fem,graphics,geometry,calculus,curvature,subdivision
Author: Peter Sharpe
Author-email: Peter Sharpe <peterdsharpe@gmail.com>
License: Apache-2.0
Classifier: Development Status :: 4 - Beta
Classifier: Intended Audience :: Science/Research
Classifier: License :: OSI Approved :: Apache Software License
Classifier: Programming Language :: Python :: 3
Classifier: Programming Language :: Python :: 3.13
Classifier: Topic :: Scientific/Engineering
Classifier: Topic :: Scientific/Engineering :: Physics
Classifier: Topic :: Scientific/Engineering :: Visualization
Requires-Dist: tensordict>=0.10.0
Requires-Dist: torch>=2.9.0
Requires-Dist: torch ; extra == 'cpu'
Requires-Dist: torch ; extra == 'cu126'
Requires-Dist: torch ; extra == 'cu128'
Requires-Dist: torch ; extra == 'cu130'
Requires-Dist: ipykernel>=7.1.0 ; extra == 'dev'
Requires-Dist: ipython>=8.37.0 ; extra == 'dev'
Requires-Dist: pytest>=9.0.0 ; extra == 'dev'
Requires-Dist: numpy>=2.2.6 ; extra == 'dev'
Requires-Dist: pyvista[all]>=0.46.4 ; extra == 'dev'
Requires-Dist: trame>=3.12.0 ; extra == 'dev'
Requires-Dist: matplotlib>=3.10.7 ; extra == 'dev'
Requires-Dist: coverage>=7.11.3 ; extra == 'dev'
Requires-Dist: pytest-cov>=7.0.0 ; extra == 'dev'
Requires-Dist: scipy>=1.15.3 ; extra == 'dev'
Requires-Dist: pyacvd>=0.2.10 ; extra == 'dev'
Requires-Dist: matplotlib>=3.10.7 ; extra == 'io'
Requires-Dist: numpy>=2.2.6 ; extra == 'io'
Requires-Dist: pyvista>=0.46.4 ; extra == 'io'
Requires-Dist: pyacvd>=0.2.10 ; extra == 'remeshing'
Requires-Python: >=3.10
Project-URL: Discussions, https://github.com/peterdsharpe/torchmesh/discussions
Project-URL: Documentation, https://github.com/peterdsharpe/torchmesh
Project-URL: Homepage, https://github.com/peterdsharpe/torchmesh
Project-URL: Issues, https://github.com/peterdsharpe/torchmesh/issues
Project-URL: Repository, https://github.com/peterdsharpe/torchmesh
Provides-Extra: cpu
Provides-Extra: cu126
Provides-Extra: cu128
Provides-Extra: cu130
Provides-Extra: dev
Provides-Extra: io
Provides-Extra: remeshing
